mirt/__init__.py
mirt/_rust_backend.py
mirt/_version.py
mirt/cat/__init__.py
mirt/cat/content.py
mirt/cat/engine.py
mirt/cat/exposure.py
mirt/cat/results.py
mirt/cat/selection.py
mirt/cat/stopping.py
mirt/diagnostics/__init__.py
mirt/diagnostics/_utils.py
mirt/diagnostics/comparison.py
mirt/diagnostics/dif.py
mirt/diagnostics/drf.py
mirt/diagnostics/dtf.py
mirt/diagnostics/itemfit.py
mirt/diagnostics/ld.py
mirt/diagnostics/modelfit.py
mirt/diagnostics/personfit.py
mirt/diagnostics/residuals.py
mirt/diagnostics/sibtest.py
mirt/estimation/__init__.py
mirt/estimation/base.py
mirt/estimation/constraints.py
mirt/estimation/em.py
mirt/estimation/latent_density.py
mirt/estimation/mcem.py
mirt/estimation/mcmc.py
mirt/estimation/mixed.py
mirt/estimation/priors.py
mirt/estimation/quadrature.py
mirt/estimation/standard_errors.py
mirt/estimation/weighted.py
mirt/exceptions.py
mirt/mirt_rs.cpython-312-darwin.so
mirt/models/__init__.py
mirt/models/base.py
mirt/models/bifactor.py
mirt/models/cdm.py
mirt/models/compensatory.py
mirt/models/custom.py
mirt/models/dichotomous.py
mirt/models/mixture.py
mirt/models/multidimensional.py
mirt/models/nested.py
mirt/models/nonparametric.py
mirt/models/polytomous.py
mirt/models/sequential.py
mirt/models/testlet.py
mirt/models/unfolding.py
mirt/models/zeroinflated.py
mirt/multigroup.py
mirt/plotting.py
mirt/results/__init__.py
mirt/results/fit_result.py
mirt/results/score_result.py
mirt/scoring/__init__.py
mirt/scoring/eap.py
mirt/scoring/eapsum.py
mirt/scoring/map.py
mirt/scoring/ml.py
mirt/scoring/wle.py
mirt/typing.py
mirt/utils/__init__.py
mirt/utils/batch.py
mirt/utils/bootstrap.py
mirt/utils/calibration.py
mirt/utils/classical.py
mirt/utils/clinical.py
mirt/utils/confidence.py
mirt/utils/cv.py
mirt/utils/data.py
mirt/utils/dataframe.py
mirt/utils/datasets.py
mirt/utils/empirical.py
mirt/utils/extraction.py
mirt/utils/imputation.py
mirt/utils/information.py
mirt/utils/multidimensional.py
mirt/utils/numeric.py
mirt/utils/plausible.py
mirt-1.0.2.dist-info/METADATA
mirt-1.0.2.dist-info/WHEEL
mirt-1.0.2.dist-info/licenses/LICENSE
mirt-1.0.2.dist-info/RECORD
