Metadata-Version: 2.4
Name: mirt
Version: 1.0.2
Classifier: Development Status :: 5 - Production/Stable
Classifier: Intended Audience :: Science/Research
Classifier: License :: OSI Approved :: MIT License
Classifier: Operating System :: OS Independent
Classifier: Programming Language :: Python :: 3
Classifier: Programming Language :: Python :: 3.11
Classifier: Programming Language :: Python :: 3.12
Classifier: Programming Language :: Python :: 3.13
Classifier: Programming Language :: Python :: 3.14
Classifier: Topic :: Scientific/Engineering
Classifier: Topic :: Scientific/Engineering :: Mathematics
Classifier: Typing :: Typed
Requires-Dist: numpy>=1.24
Requires-Dist: scipy>=1.9
Requires-Dist: pytest>=7.0 ; extra == 'dev'
Requires-Dist: pytest-cov>=4.0 ; extra == 'dev'
Requires-Dist: black>=23.0 ; extra == 'dev'
Requires-Dist: ruff>=0.1 ; extra == 'dev'
Requires-Dist: mypy>=1.0 ; extra == 'dev'
Requires-Dist: pandas>=1.5 ; extra == 'dev'
Requires-Dist: polars>=0.20 ; extra == 'dev'
Requires-Dist: maturin>=1.4 ; extra == 'dev'
Requires-Dist: sphinx>=6.0 ; extra == 'docs'
Requires-Dist: sphinx-rtd-theme>=1.0 ; extra == 'docs'
Requires-Dist: numpydoc>=1.5 ; extra == 'docs'
Requires-Dist: pandas>=1.5 ; extra == 'pandas'
Requires-Dist: polars>=0.20 ; extra == 'polars'
Provides-Extra: dev
Provides-Extra: docs
Provides-Extra: pandas
Provides-Extra: polars
License-File: LICENSE
Summary: Multidimensional Item Response Theory for Python
Keywords: item response theory,IRT,psychometrics,educational measurement,latent trait models,Rasch,graded response model
Author-email: Cameron Lyons <cameron@cameronlyons.com>
License: MIT
Requires-Python: >=3.11
Project-URL: Documentation, https://github.com/Cameron-Lyons/mirt#readme
Project-URL: Homepage, https://github.com/Cameron-Lyons/mirt
Project-URL: Repository, https://github.com/Cameron-Lyons/mirt
